core/__init__.py
core/core.abi3.so
quantrs2_core_extension-0.1.0a5.dist-info/METADATA
quantrs2_core_extension-0.1.0a5.dist-info/WHEEL
quantrs2_core_extension-0.1.0a5.dist-info/RECORD
