Metadata-Version: 2.4
Name: quantrs2-core-extension
Version: 0.1.0a5
Classifier: Development Status :: 3 - Alpha
Classifier: Intended Audience :: Science/Research
Classifier: License :: OSI Approved :: MIT License
Classifier: License :: OSI Approved :: Apache Software License
Classifier: Operating System :: OS Independent
Classifier: Programming Language :: Python :: 3
Classifier: Programming Language :: Python :: 3.8
Classifier: Programming Language :: Python :: 3.9
Classifier: Programming Language :: Python :: 3.10
Classifier: Programming Language :: Python :: 3.11
Classifier: Programming Language :: Python :: 3.12
Classifier: Programming Language :: Rust
Classifier: Topic :: Scientific/Engineering :: Physics
Classifier: Topic :: Scientific/Engineering :: Chemistry
Classifier: Topic :: Software Development :: Libraries :: Python Modules
Requires-Dist: numpy>=1.20.0
Requires-Dist: pytest>=6.0 ; extra == 'test'
Requires-Dist: pytest-benchmark ; extra == 'test'
Requires-Dist: jupyter ; extra == 'jupyter'
Requires-Dist: matplotlib ; extra == 'jupyter'
Requires-Dist: seaborn ; extra == 'jupyter'
Requires-Dist: maturin>=1.0 ; extra == 'dev'
Requires-Dist: black ; extra == 'dev'
Requires-Dist: isort ; extra == 'dev'
Requires-Dist: pytest ; extra == 'dev'
Provides-Extra: test
Provides-Extra: jupyter
Provides-Extra: dev
Summary: Python bindings for QuantRS2-Core quantum computing framework
Keywords: quantum,computing,quantum-gates,quantum-circuits,physics,simulation
Author: QuantRS2 Contributors
Author-email: "QuantRS2 Contributors (Team KitaSan)" <info@kitasan.io>
License: MIT OR Apache-2.0
Requires-Python: >=3.8
Project-URL: Homepage, https://github.com/cool-japan/quantrs
Project-URL: Repository, https://github.com/cool-japan/quantrs
Project-URL: Documentation, https://pypi.org/project/quantrs2-core/
Project-URL: Issues, https://github.com/cool-japan/quantrs/issues
